spark_partition_server/__init__.py
spark_partition_server/cluster.py
spark_partition_server/coordinator.py
spark_partition_server/partition_server.py
spark_partition_server/thread_utils.py
spark_partition_server/utils.py
spark_partition_server-0.1.5.dist-info/DESCRIPTION.rst
spark_partition_server-0.1.5.dist-info/METADATA
spark_partition_server-0.1.5.dist-info/RECORD
spark_partition_server-0.1.5.dist-info/WHEEL
spark_partition_server-0.1.5.dist-info/metadata.json
spark_partition_server-0.1.5.dist-info/top_level.txt
