Metadata-Version: 2.0
Name: spark-partition-server
Version: 0.1.5
Summary: Simple Python components for launching and managing servers on a running Spark cluster
Home-page: http://github.com/pumpikano/spark-partition-server
Author: Clayton Mellina
Author-email: cemellina@gmail.com
License: Apache-2.0
Keywords: spark,partition server,spark cluster,flask,distributed computing
Platform: Windows
Platform: Linux
Platform: Solaris
Platform: Mac OS-X
Platform: Unix
Classifier: License :: OSI Approved :: Apache Software License
Classifier: Intended Audience :: Developers
Classifier: Intended Audience :: Science/Research
Classifier: Natural Language :: English
Classifier: Operating System :: MacOS :: MacOS X
Classifier: Operating System :: Microsoft :: Windows
Classifier: Operating System :: POSIX
Classifier: Operating System :: POSIX
Classifier: Operating System :: Unix
Classifier: Programming Language :: Python :: 2.7
Classifier: Topic :: Scientific/Engineering
Classifier: Topic :: Software Development
Requires-Dist: flask (>=0.10.0)
Requires-Dist: requests (>=2.5.0)
